[
    {
        "descriptionForUrl": "light-panels",
        "categoryId": "48383",
        "pageNumber": 1,
        "filters": []
    },
    {
        "descriptionForUrl": "floodlights-led",
        "categoryId": "48384",
        "pageNumber": 1,
        "filters": []
    },
    {
        "descriptionForUrl": "ring-lights",
        "categoryId": "48386",
        "pageNumber": 1,
        "filters": []
    },
    {
        "descriptionForUrl": "LED-Light-Sources",
        "categoryId": "12248",
        "pageNumber": 1,
        "filters": []
    },
    {
        "descriptionForUrl": "fresnels",
        "categoryId": "48387",
        "pageNumber": 1,
        "filters": []
    },
    {
        "descriptionForUrl": "monolight-style",
        "categoryId": "48388",
        "pageNumber": 1,
        "filters": []
    },
    {
        "descriptionForUrl": "outdoor-spotlights",
        "categoryId": "48389",
        "pageNumber": 1,
        "filters": []
    },
    {
        "descriptionForUrl": "par-lights",
        "categoryId": "48390",
        "pageNumber": 1,
        "filters": []
    },
    {
        "descriptionForUrl": "light-wands-led-tubes",
        "categoryId": "48391",
        "pageNumber": 1,
        "filters": []
    },
    {
        "descriptionForUrl": "border-strip-cyc-lights",
        "categoryId": "48392",
        "pageNumber": 1,
        "filters": []
    },
    {
        "descriptionForUrl": "on-camera-lights",
        "categoryId": "48393",
        "pageNumber": 1,
        "filters": []
    },
    {
        "descriptionForUrl": "special-designs",
        "categoryId": "48394",
        "pageNumber": 1,
        "filters": []
    },
    {
        "descriptionForUrl": "dj-effects-lights",
        "categoryId": "48395",
        "pageNumber": 1,
        "filters": []
    },
    {
        "descriptionForUrl": "stage-lighting",
        "categoryId": "48396",
        "pageNumber": 1,
        "filters": []
    },
    {
        "descriptionForUrl": "architectural-lighting",
        "categoryId": "48397",
        "pageNumber": 1,
        "filters": []
    },
    {
        "descriptionForUrl": "ellipsoidal-light",
        "categoryId": "48398",
        "pageNumber": 1,
        "filters": []
    },
    {
        "descriptionForUrl": "Light-Sources",
        "categoryId": "1201",
        "pageNumber": 1,
        "filters": []
    },
    {
        "descriptionForUrl": "fresnels",
        "categoryId": "48568",
        "pageNumber": 1,
        "filters": []
    },
    {
        "descriptionForUrl": "floodlights",
        "categoryId": "48457",
        "pageNumber": 1,
        "filters": []
    },
    {
        "descriptionForUrl": "focusing-floods",
        "categoryId": "48741",
        "pageNumber": 1,
        "filters": []
    },
    {
        "descriptionForUrl": "Lights-Kits",
        "categoryId": "2247",
        "pageNumber": 1,
        "filters": []
    },
    {
        "descriptionForUrl": "spotlights",
        "categoryId": "48458",
        "pageNumber": 1,
        "filters": []
    },
    {
        "descriptionForUrl": "soft-lights",
        "categoryId": "48743",
        "pageNumber": 1,
        "filters": []
    },
    {
        "descriptionForUrl": "softbox-lights",
        "categoryId": "48742",
        "pageNumber": 1,
        "filters": []
    },
    {
        "descriptionForUrl": "stage-lighting",
        "categoryId": "48746",
        "pageNumber": 1,
        "filters": []
    },
    {
        "descriptionForUrl": "dj-effects-lights",
        "categoryId": "48747",
        "pageNumber": 1,
        "filters": []
    },
    {
        "descriptionForUrl": "architectural-lighting",
        "categoryId": "48748",
        "pageNumber": 1,
        "filters": []
    },
    {
        "descriptionForUrl": "on-camera-lights",
        "categoryId": "48745",
        "pageNumber": 1,
        "filters": []
    },
    {
        "descriptionForUrl": "hmi-plasma-light",
        "categoryId": "1377",
        "pageNumber": 1,
        "filters": []
    },
    {
        "descriptionForUrl": "dj-party-lights-led",
        "categoryId": "18875",
        "pageNumber": 1,
        "filters": []
    },
    {
        "descriptionForUrl": "par-lights",
        "categoryId": "51870",
        "pageNumber": 1,
        "filters": []
    },
    {
        "descriptionForUrl": "linear-bar-lights",
        "categoryId": "51872",
        "pageNumber": 1,
        "filters": []
    },
    {
        "descriptionForUrl": "led-strips",
        "categoryId": "51874",
        "pageNumber": 1,
        "filters": []
    },
    {
        "descriptionForUrl": "spotlights",
        "categoryId": "51873",
        "pageNumber": 1,
        "filters": []
    },
    {
        "descriptionForUrl": "moving-heads",
        "categoryId": "51871",
        "pageNumber": 1,
        "filters": []
    },
    {
        "descriptionForUrl": "dj-lighting-scanners",
        "categoryId": "51875",
        "pageNumber": 1,
        "filters": []
    },
    {
        "descriptionForUrl": "gobo-projectors",
        "categoryId": "51876",
        "pageNumber": 1,
        "filters": []
    },
    {
        "descriptionForUrl": "black-lights-uv",
        "categoryId": "51881",
        "pageNumber": 1,
        "filters": []
    },
    {
        "descriptionForUrl": "strobes",
        "categoryId": "51882",
        "pageNumber": 1,
        "filters": []
    },
    {
        "descriptionForUrl": "specialized-effects",
        "categoryId": "52391",
        "pageNumber": 1,
        "filters": []
    },
    {
        "descriptionForUrl": "dj-lighting-kits",
        "categoryId": "53118",
        "pageNumber": 1,
        "filters": []
    },
    {
        "descriptionForUrl": "stage-spot-lights",
        "categoryId": "6435",
        "pageNumber": 1,
        "filters": []
    },
    {
        "descriptionForUrl": "architectural-lights",
        "categoryId": "27098",
        "pageNumber": 1,
        "filters": []
    },
    {
        "descriptionForUrl": "dj-lighting-accessories",
        "categoryId": "27495",
        "pageNumber": 1,
        "filters": []
    },
    {
        "descriptionForUrl": "architectural-lighting-accessories",
        "categoryId": "28048",
        "pageNumber": 1,
        "filters": []
    },
    {
        "descriptionForUrl": "work-lights",
        "categoryId": "17882",
        "pageNumber": 1,
        "filters": []
    },
    {
        "descriptionForUrl": "Monolights",
        "categoryId": "1225",
        "pageNumber": 1,
        "filters": []
    },
    {
        "descriptionForUrl": "Flash-Heads",
        "categoryId": "1211",
        "pageNumber": 1,
        "filters": []
    },
    {
        "descriptionForUrl": "Strobe-Power-Packs",
        "categoryId": "20390",
        "pageNumber": 1,
        "filters": []
    },
    {
        "descriptionForUrl": "Kits",
        "categoryId": "2250",
        "pageNumber": 1,
        "filters": []
    },
    {
        "descriptionForUrl": "Slave-Strobes-AC-DC",
        "categoryId": "1239",
        "pageNumber": 1,
        "filters": []
    },
    {
        "descriptionForUrl": "detachable-camera-flash-external",
        "categoryId": "643",
        "pageNumber": 1,
        "filters": []
    },
    {
        "descriptionForUrl": "On-Flash-Light-Controls",
        "categoryId": "655",
        "pageNumber": 1,
        "filters": []
    },
    {
        "descriptionForUrl": "Adapters",
        "categoryId": "8946",
        "pageNumber": 1,
        "filters": []
    },
    {
        "descriptionForUrl": "ttl-cables",
        "categoryId": "654",
        "pageNumber": 1,
        "filters": []
    },
    {
        "descriptionForUrl": "Accessories-for-Macro-Ringlight-Flashes",
        "categoryId": "5648",
        "pageNumber": 1,
        "filters": []
    },
    {
        "descriptionForUrl": "pc-hot-shoe-adapters",
        "categoryId": "652",
        "pageNumber": 1,
        "filters": []
    },
    {
        "descriptionForUrl": "Sync-Cords",
        "categoryId": "1214",
        "pageNumber": 1,
        "filters": []
    },
    {
        "descriptionForUrl": "camera-flash-cases-pouches",
        "categoryId": "252",
        "pageNumber": 1,
        "filters": []
    },
    {
        "descriptionForUrl": "Other-Flash-Accessories",
        "categoryId": "658",
        "pageNumber": 1,
        "filters": []
    },
    {
        "descriptionForUrl": "hot-cold-shoe-mounts-adapters",
        "categoryId": "18944",
        "pageNumber": 1,
        "filters": []
    },
    {
        "descriptionForUrl": "extended-warranties",
        "categoryId": "37331",
        "pageNumber": 1,
        "filters": []
    },
    {
        "descriptionForUrl": "On-Camera-Lights",
        "categoryId": "2026",
        "pageNumber": 1,
        "filters": []
    },
    {
        "descriptionForUrl": "Batteries-Power",
        "categoryId": "9832",
        "pageNumber": 1,
        "filters": []
    },
    {
        "descriptionForUrl": "Adapters-Cables",
        "categoryId": "3685",
        "pageNumber": 1,
        "filters": []
    },
    {
        "descriptionForUrl": "Light-Controls",
        "categoryId": "3678",
        "pageNumber": 1,
        "filters": []
    },
    {
        "descriptionForUrl": "Background-Lighting-Kits",
        "categoryId": "12293",
        "pageNumber": 1,
        "filters": []
    },
    {
        "descriptionForUrl": "Mounts-Brackets",
        "categoryId": "3686",
        "pageNumber": 1,
        "filters": []
    },
    {
        "descriptionForUrl": "articulating-camera-arms-monitor-mounts",
        "categoryId": "10461",
        "pageNumber": 1,
        "filters": []
    },
    {
        "descriptionForUrl": "Video-Camera-Light-Lamps",
        "categoryId": "2185",
        "pageNumber": 1,
        "filters": []
    },
    {
        "descriptionForUrl": "grip-gloves",
        "categoryId": "31441",
        "pageNumber": 1,
        "filters": []
    },
    {
        "descriptionForUrl": "Other-Accessories",
        "categoryId": "3679",
        "pageNumber": 1,
        "filters": []
    },
    {
        "descriptionForUrl": "flash-triggers",
        "categoryId": "1174",
        "pageNumber": 1,
        "filters": []
    },
    {
        "descriptionForUrl": "Battery-Packs-Accessories",
        "categoryId": "645",
        "pageNumber": 1,
        "filters": []
    },
    {
        "descriptionForUrl": "Flash-Brackets-Accessories",
        "categoryId": "4938",
        "pageNumber": 1,
        "filters": []
    },
    {
        "descriptionForUrl": "Standard-Softboxes",
        "categoryId": "1337",
        "pageNumber": 1,
        "filters": []
    },
    {
        "descriptionForUrl": "Speed-Rings",
        "categoryId": "1381",
        "pageNumber": 1,
        "filters": []
    },
    {
        "descriptionForUrl": "Speed-Ring-Accessories",
        "categoryId": "1382",
        "pageNumber": 1,
        "filters": []
    },
    {
        "descriptionForUrl": "Eggcrates-Honeycomb-Grids",
        "categoryId": "6252",
        "pageNumber": 1,
        "filters": []
    },
    {
        "descriptionForUrl": "Front-Diffusers",
        "categoryId": "3752",
        "pageNumber": 1,
        "filters": []
    },
    {
        "descriptionForUrl": "Wands-Poles-Rods",
        "categoryId": "3751",
        "pageNumber": 1,
        "filters": []
    },
    {
        "descriptionForUrl": "Barndoors",
        "categoryId": "6251",
        "pageNumber": 1,
        "filters": []
    },
    {
        "descriptionForUrl": "Other-Softbox-Accessories",
        "categoryId": "1338",
        "pageNumber": 1,
        "filters": []
    },
    {
        "descriptionForUrl": "Umbrellas",
        "categoryId": "1325",
        "pageNumber": 1,
        "filters": []
    },
    {
        "descriptionForUrl": "Flash-Mounts-Umbrella-Mounting-Accessories",
        "categoryId": "3536",
        "pageNumber": 1,
        "filters": []
    },
    {
        "descriptionForUrl": "umbrella-diffusers",
        "categoryId": "31190",
        "pageNumber": 1,
        "filters": []
    },
    {
        "descriptionForUrl": "umbrella-grids",
        "categoryId": "35850",
        "pageNumber": 1,
        "filters": []
    },
    {
        "descriptionForUrl": "other-umbrella-accessories",
        "categoryId": "31189",
        "pageNumber": 1,
        "filters": []
    },
    {
        "descriptionForUrl": "reflectors-accessories",
        "categoryId": "31160",
        "pageNumber": 1,
        "filters": []
    },
    {
        "descriptionForUrl": "Barndoors",
        "categoryId": "1180",
        "pageNumber": 1,
        "filters": []
    },
    {
        "descriptionForUrl": "Barndoor-Accessories",
        "categoryId": "6384",
        "pageNumber": 1,
        "filters": []
    },
    {
        "descriptionForUrl": "Snoots",
        "categoryId": "6351",
        "pageNumber": 1,
        "filters": []
    },
    {
        "descriptionForUrl": "Egg-Crates-Honeycomb-Grids",
        "categoryId": "18962",
        "pageNumber": 1,
        "filters": []
    },
    {
        "descriptionForUrl": "Wire-Scrims",
        "categoryId": "1187",
        "pageNumber": 1,
        "filters": []
    },
    {
        "descriptionForUrl": "color-correction-filters-gels",
        "categoryId": "24442",
        "pageNumber": 1,
        "filters": []
    },
    {
        "descriptionForUrl": "Lighting-Filters",
        "categoryId": "1329",
        "pageNumber": 1,
        "filters": []
    },
    {
        "descriptionForUrl": "diffusers-diffusion-material",
        "categoryId": "24480",
        "pageNumber": 1,
        "filters": []
    },
    {
        "descriptionForUrl": "Filter-Diffuser-Holders",
        "categoryId": "5702",
        "pageNumber": 1,
        "filters": []
    },
    {
        "descriptionForUrl": "filter-holder-accessories",
        "categoryId": "36675",
        "pageNumber": 1,
        "filters": []
    },
    {
        "descriptionForUrl": "Projection-Attachments-Lenses",
        "categoryId": "1676",
        "pageNumber": 1,
        "filters": []
    },
    {
        "descriptionForUrl": "projection-lens-accessories",
        "categoryId": "39700",
        "pageNumber": 1,
        "filters": []
    },
    {
        "descriptionForUrl": "Gobos-Discs-Patterns",
        "categoryId": "1733",
        "pageNumber": 1,
        "filters": []
    },
    {
        "descriptionForUrl": "Accessories-for-Gobos-Patterns",
        "categoryId": "1734",
        "pageNumber": 1,
        "filters": []
    },
    {
        "descriptionForUrl": "Glass",
        "categoryId": "1672",
        "pageNumber": 1,
        "filters": []
    },
    {
        "descriptionForUrl": "Frames-for-Frame-Panel-Reflectors",
        "categoryId": "1340",
        "pageNumber": 1,
        "filters": []
    },
    {
        "descriptionForUrl": "Fabrics-for-Frame-Panel-Reflectors",
        "categoryId": "1341",
        "pageNumber": 1,
        "filters": []
    },
    {
        "descriptionForUrl": "Frame-Panel-Reflector-Kits",
        "categoryId": "1339",
        "pageNumber": 1,
        "filters": []
    },
    {
        "descriptionForUrl": "butterfly-panel-reflector-accessories",
        "categoryId": "30370",
        "pageNumber": 1,
        "filters": []
    },
    {
        "descriptionForUrl": "reflector-bounce-boards",
        "categoryId": "12974",
        "pageNumber": 1,
        "filters": []
    },
    {
        "descriptionForUrl": "Collapsible-Reflectors",
        "categoryId": "1327",
        "pageNumber": 1,
        "filters": []
    },
    {
        "descriptionForUrl": "Accessories-for-Collapsible-Reflectors",
        "categoryId": "1328",
        "pageNumber": 1,
        "filters": []
    },
    {
        "descriptionForUrl": "flags-dots-cucoloris",
        "categoryId": "28876",
        "pageNumber": 1,
        "filters": []
    },
    {
        "descriptionForUrl": "Filter-Diffuser-Holders",
        "categoryId": "5706",
        "pageNumber": 1,
        "filters": []
    },
    {
        "descriptionForUrl": "Lightstands",
        "categoryId": "5799",
        "pageNumber": 1,
        "filters": []
    },
    {
        "descriptionForUrl": "boom-arms-stands-equipment",
        "categoryId": "1362",
        "pageNumber": 1,
        "filters": []
    },
    {
        "descriptionForUrl": "trussing-equipment",
        "categoryId": "27767",
        "pageNumber": 1,
        "filters": []
    },
    {
        "descriptionForUrl": "Lightstand-Risers-Columns",
        "categoryId": "2448",
        "pageNumber": 1,
        "filters": []
    },
    {
        "descriptionForUrl": "Extension-Poles",
        "categoryId": "1371",
        "pageNumber": 1,
        "filters": []
    },
    {
        "descriptionForUrl": "Lightstand-Bases",
        "categoryId": "2449",
        "pageNumber": 1,
        "filters": []
    },
    {
        "descriptionForUrl": "Casters-Wheel-Sets",
        "categoryId": "1370",
        "pageNumber": 1,
        "filters": []
    },
    {
        "descriptionForUrl": "Studs-Receptors-Pins",
        "categoryId": "1358",
        "pageNumber": 1,
        "filters": []
    },
    {
        "descriptionForUrl": "Adapters",
        "categoryId": "1350",
        "pageNumber": 1,
        "filters": []
    },
    {
        "descriptionForUrl": "Clamps",
        "categoryId": "1353",
        "pageNumber": 1,
        "filters": []
    },
    {
        "descriptionForUrl": "Brackets",
        "categoryId": "1352",
        "pageNumber": 1,
        "filters": []
    },
    {
        "descriptionForUrl": "Grip-Heads",
        "categoryId": "1355",
        "pageNumber": 1,
        "filters": []
    },
    {
        "descriptionForUrl": "Arms",
        "categoryId": "1351",
        "pageNumber": 1,
        "filters": []
    },
    {
        "descriptionForUrl": "Grip-Accessories",
        "categoryId": "1700",
        "pageNumber": 1,
        "filters": []
    },
    {
        "descriptionForUrl": "Suction-Cups-Accessories",
        "categoryId": "8110",
        "pageNumber": 1,
        "filters": []
    },
    {
        "descriptionForUrl": "Sandbags-Weight-Bags",
        "categoryId": "1373",
        "pageNumber": 1,
        "filters": []
    },
    {
        "descriptionForUrl": "Other-Accessories-for-Lightstands",
        "categoryId": "2227",
        "pageNumber": 1,
        "filters": []
    },
    {
        "descriptionForUrl": "AC-DC-Power-Supplies",
        "categoryId": "20391",
        "pageNumber": 1,
        "filters": []
    },
    {
        "descriptionForUrl": "dc-power-supplies",
        "categoryId": "27725",
        "pageNumber": 1,
        "filters": []
    },
    {
        "descriptionForUrl": "electronic-ballasts",
        "categoryId": "20387",
        "pageNumber": 1,
        "filters": []
    },
    {
        "descriptionForUrl": "power-inverters",
        "categoryId": "28678",
        "pageNumber": 1,
        "filters": []
    },
    {
        "descriptionForUrl": "v-mount-batteries-lighting",
        "categoryId": "27617",
        "pageNumber": 1,
        "filters": []
    },
    {
        "descriptionForUrl": "Batteries",
        "categoryId": "20389",
        "pageNumber": 1,
        "filters": []
    },
    {
        "descriptionForUrl": "battery-adapter-plates",
        "categoryId": "27613",
        "pageNumber": 1,
        "filters": []
    },
    {
        "descriptionForUrl": "battery-charger-accessories",
        "categoryId": "27691",
        "pageNumber": 1,
        "filters": []
    },
    {
        "descriptionForUrl": "Power-Cables",
        "categoryId": "20392",
        "pageNumber": 1,
        "filters": []
    },
    {
        "descriptionForUrl": "dmx-cables",
        "categoryId": "27973",
        "pageNumber": 1,
        "filters": []
    },
    {
        "descriptionForUrl": "Cables",
        "categoryId": "11884",
        "pageNumber": 1,
        "filters": []
    },
    {
        "descriptionForUrl": "AC-Power-Extension-Cords",
        "categoryId": "1773",
        "pageNumber": 1,
        "filters": []
    },
    {
        "descriptionForUrl": "wireless-flash-triggers-radio-transmitters",
        "categoryId": "8007",
        "pageNumber": 1,
        "filters": []
    },
    {
        "descriptionForUrl": "Motor-Cords",
        "categoryId": "2832",
        "pageNumber": 1,
        "filters": []
    },
    {
        "descriptionForUrl": "Slave-Accessories",
        "categoryId": "8009",
        "pageNumber": 1,
        "filters": []
    },
    {
        "descriptionForUrl": "Optical-Slaves",
        "categoryId": "1736",
        "pageNumber": 1,
        "filters": []
    },
    {
        "descriptionForUrl": "light-meters-accessories",
        "categoryId": "21923",
        "pageNumber": 1,
        "filters": []
    },
    {
        "descriptionForUrl": "Bulbs-Lamps",
        "categoryId": "6280",
        "pageNumber": 1,
        "filters": []
    },
    {
        "descriptionForUrl": "Cases-Covers",
        "categoryId": "308",
        "pageNumber": 1,
        "filters": []
    },
    {
        "descriptionForUrl": "Lightstand-Umbrella-Cases",
        "categoryId": "215",
        "pageNumber": 1,
        "filters": []
    },
    {
        "descriptionForUrl": "Softbox-Cases",
        "categoryId": "6349",
        "pageNumber": 1,
        "filters": []
    },
    {
        "descriptionForUrl": "Lamp-Cases-Accessories",
        "categoryId": "8476",
        "pageNumber": 1,
        "filters": []
    },
    {
        "descriptionForUrl": "case-cover-accessories",
        "categoryId": "43850",
        "pageNumber": 1,
        "filters": []
    },
    {
        "descriptionForUrl": "camera-hard-cases-waterproof",
        "categoryId": "16460",
        "pageNumber": 1,
        "filters": []
    },
    {
        "descriptionForUrl": "watertight-case-dividers",
        "categoryId": "31197",
        "pageNumber": 1,
        "filters": []
    },
    {
        "descriptionForUrl": "watertight-case-organizers",
        "categoryId": "31199",
        "pageNumber": 1,
        "filters": []
    },
    {
        "descriptionForUrl": "watertight-case-foam-inserts",
        "categoryId": "31198",
        "pageNumber": 1,
        "filters": []
    },
    {
        "descriptionForUrl": "Hard-Watertight-Case-Accessories",
        "categoryId": "16645",
        "pageNumber": 1,
        "filters": []
    },
    {
        "descriptionForUrl": "Carts-Handtrucks",
        "categoryId": "224",
        "pageNumber": 1,
        "filters": []
    },
    {
        "descriptionForUrl": "hand-truck-accessories",
        "categoryId": "34026",
        "pageNumber": 1,
        "filters": []
    },
    {
        "descriptionForUrl": "case-and-luggage-locks",
        "categoryId": "31552",
        "pageNumber": 1,
        "filters": []
    },
    {
        "descriptionForUrl": "lighting-consoles-controllers",
        "categoryId": "26124",
        "pageNumber": 1,
        "filters": []
    },
    {
        "descriptionForUrl": "Control-Consoles",
        "categoryId": "8156",
        "pageNumber": 1,
        "filters": []
    },
    {
        "descriptionForUrl": "Projection-Accessories",
        "categoryId": "1675",
        "pageNumber": 1,
        "filters": []
    },
    {
        "descriptionForUrl": "lighting-console-accessories",
        "categoryId": "26125",
        "pageNumber": 1,
        "filters": []
    },
    {
        "descriptionForUrl": "Sockets-Switches",
        "categoryId": "11887",
        "pageNumber": 1,
        "filters": []
    },
    {
        "descriptionForUrl": "Remote-Controls",
        "categoryId": "1674",
        "pageNumber": 1,
        "filters": []
    },
    {
        "descriptionForUrl": "yokes-operating-poles",
        "categoryId": "27852",
        "pageNumber": 1,
        "filters": []
    },
    {
        "descriptionForUrl": "Wireguards-Safety-Screens",
        "categoryId": "11327",
        "pageNumber": 1,
        "filters": []
    },
    {
        "descriptionForUrl": "Lighting-Books-Tutorials",
        "categoryId": "7756",
        "pageNumber": 1,
        "filters": []
    },
    {
        "descriptionForUrl": "Flashlights",
        "categoryId": "6898",
        "pageNumber": 1,
        "filters": []
    },
    {
        "descriptionForUrl": "keychain-flashlights-mini-led",
        "categoryId": "26370",
        "pageNumber": 1,
        "filters": []
    },
    {
        "descriptionForUrl": "headlamps",
        "categoryId": "25145",
        "pageNumber": 1,
        "filters": []
    },
    {
        "descriptionForUrl": "portable-lights-led",
        "categoryId": "26388",
        "pageNumber": 1,
        "filters": []
    },
    {
        "descriptionForUrl": "bicycle-lights",
        "categoryId": "27793",
        "pageNumber": 1,
        "filters": []
    },
    {
        "descriptionForUrl": "indoor-area-lighting",
        "categoryId": "28562",
        "pageNumber": 1,
        "filters": []
    },
    {
        "descriptionForUrl": "lanterns",
        "categoryId": "26368",
        "pageNumber": 1,
        "filters": []
    },
    {
        "descriptionForUrl": "batteries-power-accessories",
        "categoryId": "27090",
        "pageNumber": 1,
        "filters": []
    },
    {
        "descriptionForUrl": "Standard-Rechargeable-Batteries-Chargers",
        "categoryId": "436",
        "pageNumber": 1,
        "filters": []
    },
    {
        "descriptionForUrl": "button-coin-cell-batteries",
        "categoryId": "27257",
        "pageNumber": 1,
        "filters": []
    },
    {
        "descriptionForUrl": "carrying-mounting-gear",
        "categoryId": "27091",
        "pageNumber": 1,
        "filters": []
    },
    {
        "descriptionForUrl": "holsters",
        "categoryId": "27095",
        "pageNumber": 1,
        "filters": []
    },
    {
        "descriptionForUrl": "conversion-upgrades",
        "categoryId": "27092",
        "pageNumber": 1,
        "filters": []
    },
    {
        "descriptionForUrl": "reflectors-shrouds",
        "categoryId": "27097",
        "pageNumber": 1,
        "filters": []
    },
    {
        "descriptionForUrl": "filters-lenses",
        "categoryId": "27094",
        "pageNumber": 1,
        "filters": []
    },
    {
        "descriptionForUrl": "lamps-leds",
        "categoryId": "27096",
        "pageNumber": 1,
        "filters": []
    },
    {
        "descriptionForUrl": "diffusers",
        "categoryId": "27093",
        "pageNumber": 1,
        "filters": []
    },
    {
        "descriptionForUrl": "other-accessories",
        "categoryId": "27089",
        "pageNumber": 1,
        "filters": []
    },
    {
        "descriptionForUrl": "Cable-Management-Accessories",
        "categoryId": "8313",
        "pageNumber": 1,
        "filters": []
    },
    {
        "descriptionForUrl": "Multi-Purpose-Tools",
        "categoryId": "2433",
        "pageNumber": 1,
        "filters": []
    },
    {
        "descriptionForUrl": "multi-tools",
        "categoryId": "22637",
        "pageNumber": 1,
        "filters": []
    },
    {
        "descriptionForUrl": "Safety-Security-Cables",
        "categoryId": "16217",
        "pageNumber": 1,
        "filters": []
    },
    {
        "descriptionForUrl": "tools-accessories",
        "categoryId": "44185",
        "pageNumber": 1,
        "filters": []
    },
    {
        "descriptionForUrl": "seamless-paper",
        "categoryId": "23680",
        "pageNumber": 1,
        "filters": []
    },
    {
        "descriptionForUrl": "Chroma-Key-Backgrounds",
        "categoryId": "6446",
        "pageNumber": 1,
        "filters": []
    },
    {
        "descriptionForUrl": "muslin-fabric-backgrounds",
        "categoryId": "23716",
        "pageNumber": 1,
        "filters": []
    },
    {
        "descriptionForUrl": "collapsible-backgrounds",
        "categoryId": "23697",
        "pageNumber": 1,
        "filters": []
    },
    {
        "descriptionForUrl": "vinyl-pvc-backgrounds",
        "categoryId": "23694",
        "pageNumber": 1,
        "filters": []
    },
    {
        "descriptionForUrl": "Backgrounds-Backdrops",
        "categoryId": "16284",
        "pageNumber": 1,
        "filters": []
    },
    {
        "descriptionForUrl": "Floors",
        "categoryId": "2429",
        "pageNumber": 1,
        "filters": []
    },
    {
        "descriptionForUrl": "gold-silver-shimmer-backdrops",
        "categoryId": "6032",
        "pageNumber": 1,
        "filters": []
    },
    {
        "descriptionForUrl": "Background-Supports",
        "categoryId": "1396",
        "pageNumber": 1,
        "filters": []
    },
    {
        "descriptionForUrl": "Background-Support-Accessories",
        "categoryId": "4815",
        "pageNumber": 1,
        "filters": []
    },
    {
        "descriptionForUrl": "Autopoles",
        "categoryId": "1407",
        "pageNumber": 1,
        "filters": []
    },
    {
        "descriptionForUrl": "Shooting-Tables",
        "categoryId": "1409",
        "pageNumber": 1,
        "filters": []
    },
    {
        "descriptionForUrl": "Tents-Domes-Blinds",
        "categoryId": "1410",
        "pageNumber": 1,
        "filters": []
    },
    {
        "descriptionForUrl": "Shooting-Table-Accessories",
        "categoryId": "6346",
        "pageNumber": 1,
        "filters": []
    },
    {
        "descriptionForUrl": "Tabletop-Shooting-Table-Backgrounds",
        "categoryId": "12656",
        "pageNumber": 1,
        "filters": []
    },
    {
        "descriptionForUrl": "Copystands",
        "categoryId": "711",
        "pageNumber": 1,
        "filters": []
    },
    {
        "descriptionForUrl": "Accessories-for-Copystands",
        "categoryId": "713",
        "pageNumber": 1,
        "filters": []
    },
    {
        "descriptionForUrl": "Product-Turntables",
        "categoryId": "18679",
        "pageNumber": 1,
        "filters": []
    },
    {
        "descriptionForUrl": "Cycs",
        "categoryId": "14478",
        "pageNumber": 1,
        "filters": []
    },
    {
        "descriptionForUrl": "Apple-Boxes-Basso-Blocks-Wood",
        "categoryId": "1401",
        "pageNumber": 1,
        "filters": []
    },
    {
        "descriptionForUrl": "photo-booths",
        "categoryId": "26405",
        "pageNumber": 1,
        "filters": []
    },
    {
        "descriptionForUrl": "Posing-Equipment",
        "categoryId": "1408",
        "pageNumber": 1,
        "filters": []
    },
    {
        "descriptionForUrl": "Studio-Ladders",
        "categoryId": "1404",
        "pageNumber": 1,
        "filters": []
    },
    {
        "descriptionForUrl": "Gaffer-Duve-Specialty-Tapes",
        "categoryId": "1403",
        "pageNumber": 1,
        "filters": []
    },
    {
        "descriptionForUrl": "Fog-Special-Effects-Machines",
        "categoryId": "1411",
        "pageNumber": 1,
        "filters": []
    },
    {
        "descriptionForUrl": "bubble-snow-wind-machines",
        "categoryId": "34282",
        "pageNumber": 1,
        "filters": []
    },
    {
        "descriptionForUrl": "fog-juice-machine-fluids",
        "categoryId": "28879",
        "pageNumber": 1,
        "filters": []
    },
    {
        "descriptionForUrl": "special-effects-accessories",
        "categoryId": "28880",
        "pageNumber": 1,
        "filters": []
    },
    {
        "descriptionForUrl": "Special-Effects-Projectors",
        "categoryId": "16518",
        "pageNumber": 1,
        "filters": []
    },
    {
        "descriptionForUrl": "Paints",
        "categoryId": "1406",
        "pageNumber": 1,
        "filters": []
    },
    {
        "descriptionForUrl": "Other-Stage-Equipment",
        "categoryId": "2421",
        "pageNumber": 1,
        "filters": []
    },
    {
        "descriptionForUrl": "woodworking-clamps",
        "categoryId": "27957",
        "pageNumber": 1,
        "filters": []
    },
    {
        "descriptionForUrl": "Props-Special-Effects",
        "categoryId": "2427",
        "pageNumber": 1,
        "filters": []
    },
    {
        "descriptionForUrl": "Paint-Brushes",
        "categoryId": "7843",
        "pageNumber": 1,
        "filters": []
    },
    {
        "descriptionForUrl": "Rail-Systems-Accessories",
        "categoryId": "11940",
        "pageNumber": 1,
        "filters": []
    },
    {
        "descriptionForUrl": "Binoculars",
        "categoryId": "1010",
        "pageNumber": 1,
        "filters": []
    },
    {
        "descriptionForUrl": "Opera-Glasses",
        "categoryId": "8721",
        "pageNumber": 1,
        "filters": []
    },
    {
        "descriptionForUrl": "solar-viewing-binoculars",
        "categoryId": "31714",
        "pageNumber": 1,
        "filters": []
    },
    {
        "descriptionForUrl": "Binocular-Cases",
        "categoryId": "178",
        "pageNumber": 1,
        "filters": []
    },
    {
        "descriptionForUrl": "Eyepieces-Eyecups",
        "categoryId": "2622",
        "pageNumber": 1,
        "filters": []
    },
    {
        "descriptionForUrl": "Caps-Rainguards",
        "categoryId": "2623",
        "pageNumber": 1,
        "filters": []
    },
    {
        "descriptionForUrl": "Straps",
        "categoryId": "1022",
        "pageNumber": 1,
        "filters": []
    },
    {
        "descriptionForUrl": "Other-Accessories",
        "categoryId": "1024",
        "pageNumber": 1,
        "filters": []
    },
    {
        "descriptionForUrl": "Lens-Optics-Cleaning",
        "categoryId": "18804",
        "pageNumber": 1,
        "filters": []
    },
    {
        "descriptionForUrl": "Tripod-Adapters",
        "categoryId": "1023",
        "pageNumber": 1,
        "filters": []
    },
    {
        "descriptionForUrl": "tripod-adapters",
        "categoryId": "21820",
        "pageNumber": 1,
        "filters": []
    },
    {
        "descriptionForUrl": "extended-warranties",
        "categoryId": "37329",
        "pageNumber": 1,
        "filters": []
    },
    {
        "descriptionForUrl": "Refractor",
        "categoryId": "3391",
        "pageNumber": 1,
        "filters": []
    },
    {
        "descriptionForUrl": "Reflector-Newtonian-Dobsonian",
        "categoryId": "3390",
        "pageNumber": 1,
        "filters": []
    },
    {
        "descriptionForUrl": "Catadioptrics-Cassegrain",
        "categoryId": "3392",
        "pageNumber": 1,
        "filters": []
    },
    {
        "descriptionForUrl": "digital-telescopes",
        "categoryId": "52044",
        "pageNumber": 1,
        "filters": []
    },
    {
        "descriptionForUrl": "Solar-Viewing-Scopes",
        "categoryId": "8963",
        "pageNumber": 1,
        "filters": []
    },
    {
        "descriptionForUrl": "Eyepieces",
        "categoryId": "3394",
        "pageNumber": 1,
        "filters": []
    },
    {
        "descriptionForUrl": "Diagonals-Prisms-Mirrors-Holders",
        "categoryId": "3396",
        "pageNumber": 1,
        "filters": []
    },
    {
        "descriptionForUrl": "Barlow-Lenses",
        "categoryId": "3395",
        "pageNumber": 1,
        "filters": []
    },
    {
        "descriptionForUrl": "Eyepiece-Side-Adapters",
        "categoryId": "3398",
        "pageNumber": 1,
        "filters": []
    },
    {
        "descriptionForUrl": "Filters",
        "categoryId": "3400",
        "pageNumber": 1,
        "filters": []
    },
    {
        "descriptionForUrl": "Other-Eyepiece-Accessories",
        "categoryId": "3421",
        "pageNumber": 1,
        "filters": []
    },
    {
        "descriptionForUrl": "Mounts",
        "categoryId": "3401",
        "pageNumber": 1,
        "filters": []
    },
    {
        "descriptionForUrl": "Accessories-for-Mounts",
        "categoryId": "3402",
        "pageNumber": 1,
        "filters": []
    },
    {
        "descriptionForUrl": "Computerized-Accessories",
        "categoryId": "3405",
        "pageNumber": 1,
        "filters": []
    },
    {
        "descriptionForUrl": "Tripods-Piers",
        "categoryId": "3406",
        "pageNumber": 1,
        "filters": []
    },
    {
        "descriptionForUrl": "tripod-pier-accessories",
        "categoryId": "39904",
        "pageNumber": 1,
        "filters": []
    },
    {
        "descriptionForUrl": "Finderscopes-Accessories",
        "categoryId": "3399",
        "pageNumber": 1,
        "filters": []
    },
    {
        "descriptionForUrl": "Focusers",
        "categoryId": "3424",
        "pageNumber": 1,
        "filters": []
    },
    {
        "descriptionForUrl": "Telescope-Cases",
        "categoryId": "3412",
        "pageNumber": 1,
        "filters": []
    },
    {
        "descriptionForUrl": "Other-Telescope-Accessories",
        "categoryId": "3388",
        "pageNumber": 1,
        "filters": []
    },
    {
        "descriptionForUrl": "books-tutorials",
        "categoryId": "27612",
        "pageNumber": 1,
        "filters": []
    },
    {
        "descriptionForUrl": "imaging-cameras",
        "categoryId": "39697",
        "pageNumber": 1,
        "filters": []
    },
    {
        "descriptionForUrl": "astro-imaging-filters",
        "categoryId": "48642",
        "pageNumber": 1,
        "filters": []
    },
    {
        "descriptionForUrl": "filter-wheels",
        "categoryId": "48643",
        "pageNumber": 1,
        "filters": []
    },
    {
        "descriptionForUrl": "astrophotography-adapter-rings-extension-tubes",
        "categoryId": "48682",
        "pageNumber": 1,
        "filters": []
    },
    {
        "descriptionForUrl": "focal-reducers-field-flatteners",
        "categoryId": "48644",
        "pageNumber": 1,
        "filters": []
    },
    {
        "descriptionForUrl": "guiding-accessories",
        "categoryId": "48645",
        "pageNumber": 1,
        "filters": []
    },
    {
        "descriptionForUrl": "telescope-focusing-masks",
        "categoryId": "48646",
        "pageNumber": 1,
        "filters": []
    },
    {
        "descriptionForUrl": "other-astrophotography-accessories",
        "categoryId": "48683",
        "pageNumber": 1,
        "filters": []
    },
    {
        "descriptionForUrl": "smartphone-digiscoping-adapters",
        "categoryId": "39704",
        "pageNumber": 1,
        "filters": []
    },
    {
        "descriptionForUrl": "t-mount-adapters",
        "categoryId": "24706",
        "pageNumber": 1,
        "filters": []
    },
    {
        "descriptionForUrl": "star-tracker-camera-mounts",
        "categoryId": "48647",
        "pageNumber": 1,
        "filters": []
    },
    {
        "descriptionForUrl": "star-tracker-accessories",
        "categoryId": "48648",
        "pageNumber": 1,
        "filters": []
    },
    {
        "descriptionForUrl": "solar-eclipse-glasses-accessories",
        "categoryId": "32948",
        "pageNumber": 1,
        "filters": []
    },
    {
        "descriptionForUrl": "solar-filters-for-astronomical-telscopes",
        "categoryId": "33821",
        "pageNumber": 1,
        "filters": []
    },
    {
        "descriptionForUrl": "solar-telescope-accessories",
        "categoryId": "33820",
        "pageNumber": 1,
        "filters": []
    },
    {
        "descriptionForUrl": "solar-photography-filters",
        "categoryId": "34576",
        "pageNumber": 1,
        "filters": []
    },
    {
        "descriptionForUrl": "solar-eclipse-software",
        "categoryId": "36246",
        "pageNumber": 1,
        "filters": []
    },
    {
        "descriptionForUrl": "Spotting-Scopes",
        "categoryId": "1032",
        "pageNumber": 1,
        "filters": []
    },
    {
        "descriptionForUrl": "Digiscoping",
        "categoryId": "14671",
        "pageNumber": 1,
        "filters": []
    },
    {
        "descriptionForUrl": "Eyepieces",
        "categoryId": "5191",
        "pageNumber": 1,
        "filters": []
    },
    {
        "descriptionForUrl": "Spotting-Scope-Cases",
        "categoryId": "5349",
        "pageNumber": 1,
        "filters": []
    },
    {
        "descriptionForUrl": "Riflescopes",
        "categoryId": "13522",
        "pageNumber": 1,
        "filters": []
    },
    {
        "descriptionForUrl": "Accessories",
        "categoryId": "13523",
        "pageNumber": 1,
        "filters": []
    },
    {
        "descriptionForUrl": "Scope-Mounting",
        "categoryId": "19212",
        "pageNumber": 1,
        "filters": []
    },
    {
        "descriptionForUrl": "Binoculars-Scopes",
        "categoryId": "11918",
        "pageNumber": 1,
        "filters": []
    },
    {
        "descriptionForUrl": "Night-Vision-Accessories",
        "categoryId": "14381",
        "pageNumber": 1,
        "filters": []
    },
    {
        "descriptionForUrl": "Thermal-Imaging",
        "categoryId": "14349",
        "pageNumber": 1,
        "filters": []
    },
    {
        "descriptionForUrl": "general-accessories",
        "categoryId": "25910",
        "pageNumber": 1,
        "filters": []
    },
    {
        "descriptionForUrl": "compasses-gps",
        "categoryId": "25000",
        "pageNumber": 1,
        "filters": []
    },
    {
        "descriptionForUrl": "handheld-gps",
        "categoryId": "30673",
        "pageNumber": 1,
        "filters": []
    },
    {
        "descriptionForUrl": "gps",
        "categoryId": "28045",
        "pageNumber": 1,
        "filters": []
    },
    {
        "descriptionForUrl": "gps-accessories",
        "categoryId": "29121",
        "pageNumber": 1,
        "filters": []
    },
    {
        "descriptionForUrl": "knives-cutting-tools",
        "categoryId": "24998",
        "pageNumber": 1,
        "filters": []
    },
    {
        "descriptionForUrl": "sharpeners",
        "categoryId": "28108",
        "pageNumber": 1,
        "filters": []
    },
    {
        "descriptionForUrl": "emergency-tools",
        "categoryId": "28098",
        "pageNumber": 1,
        "filters": []
    },
    {
        "descriptionForUrl": "jump-starters",
        "categoryId": "28211",
        "pageNumber": 1,
        "filters": []
    },
    {
        "descriptionForUrl": "trekking-poles",
        "categoryId": "28038",
        "pageNumber": 1,
        "filters": []
    },
    {
        "descriptionForUrl": "outdoor-furniture",
        "categoryId": "28034",
        "pageNumber": 1,
        "filters": []
    },
    {
        "descriptionForUrl": "misc-field-accessories",
        "categoryId": "35068",
        "pageNumber": 1,
        "filters": []
    },
    {
        "descriptionForUrl": "wildlife-monitoring",
        "categoryId": "25135",
        "pageNumber": 1,
        "filters": []
    },
    {
        "descriptionForUrl": "apparel",
        "categoryId": "27956",
        "pageNumber": 1,
        "filters": []
    },
    {
        "descriptionForUrl": "shirts",
        "categoryId": "30919",
        "pageNumber": 1,
        "filters": []
    },
    {
        "descriptionForUrl": "headgear",
        "categoryId": "30282",
        "pageNumber": 1,
        "filters": []
    },
    {
        "descriptionForUrl": "sunglasses-goggle-accessories",
        "categoryId": "31414",
        "pageNumber": 1,
        "filters": []
    },
    {
        "descriptionForUrl": "firearms-equipment",
        "categoryId": "25137",
        "pageNumber": 1,
        "filters": []
    },
    {
        "descriptionForUrl": "maintenance-safety",
        "categoryId": "25756",
        "pageNumber": 1,
        "filters": []
    },
    {
        "descriptionForUrl": "Monoculars-Rangefinders",
        "categoryId": "17400",
        "pageNumber": 1,
        "filters": []
    },
    {
        "descriptionForUrl": "laser-rangefinders",
        "categoryId": "37565",
        "pageNumber": 1,
        "filters": []
    },
    {
        "descriptionForUrl": "compound-microscopes",
        "categoryId": "41707",
        "pageNumber": 1,
        "filters": []
    },
    {
        "descriptionForUrl": "stereo-microscopes",
        "categoryId": "41704",
        "pageNumber": 1,
        "filters": []
    },
    {
        "descriptionForUrl": "Digital-Microscopes",
        "categoryId": "12478",
        "pageNumber": 1,
        "filters": []
    },
    {
        "descriptionForUrl": "Other-Microscope-Accessories",
        "categoryId": "8217",
        "pageNumber": 1,
        "filters": []
    },
    {
        "descriptionForUrl": "slides-accessories",
        "categoryId": "41705",
        "pageNumber": 1,
        "filters": []
    },
    {
        "descriptionForUrl": "books-tutorials",
        "categoryId": "41706",
        "pageNumber": 1,
        "filters": []
    }
]